fast1dkmeans/__init__.py
fast1dkmeans/common.py
fast1dkmeans/kmeans.py
fast1dkmeans/main.py
fast1dkmeans/monge.py
fast1dkmeans/old_classes.py
fast1dkmeans/regularized_kmeans.py
fast1dkmeans/smawk.py
fast1dkmeans/smawk_iter.py
fast1dkmeans/utils.py
fast1dkmeans/tests/test_common.py
fast1dkmeans/tests/test_kmeans.py
fast1dkmeans/tests/test_main.py
fast1dkmeans/tests/test_regularized_kmeans.py
fast1dkmeans/tests/test_smawk.py
fast1dkmeans/tests/test_smawk_iter.py
fast1dkmeans/tests/utils_for_test.py
fast1dkmeans-0.1.2.dist-info/LICENSE
fast1dkmeans-0.1.2.dist-info/METADATA
fast1dkmeans-0.1.2.dist-info/WHEEL
fast1dkmeans-0.1.2.dist-info/top_level.txt
fast1dkmeans-0.1.2.dist-info/RECORD
