Metadata-Version: 2.1
Name: fast1dkmeans
Version: 0.1.2
Summary: A python package for optimal 1d k-means clustering.
Author: Felix Stamm
Author-email: felix.stamm@cssh.rwth-aachen.de
Requires-Python: >=3.8
License-File: LICENSE
Requires-Dist: numpy
Requires-Dist: numba
